{
  "parallel": false,
  "withESBD": true,
  "getPolicyTWB": false,
  "setPolicyWaitingTWB": false,
  "hiddenLogBodies": true,
  "verification": false,
  "timezone": "Asia/Aqtau",
  "environment": "localhost",
  "allureCommandlineArgs": [
    "generate",
    "./artifacts/allure-results",
    "--clean",
    "-o",
    "./artifacts/allure-report"
  ],
  "logTimeStampFormat": "YYYY-MM-DD HH:mm:ss",
  "DBTimeStampFormat": "YYYY-MM-DDTHH:mm:ss.SSSZ",
  "allureAvoidLoggingCommands": [
    "url",
    "as",
    "clicks",
    "window",
    "setLocalStorage",
    "getLocalStorage",
    "wrap",
    "logger",
    "task",
    "open",
    "type",
    "visit",
    "find",
    "xpath",
    "first",
    "isVisible",
    "isExisting",
    "isEnabled",
    "click",
    "request",
    "contains",
    "scrollTo",
    "document",
    "clear",
    "request",
    "invoke",
    "clearAllCookies",
    "scrollIntoView"
  ],
  "servers": "[{\"url\":\"https://testesbd.mkb.kz:8077/IICwebservice.asmx\",\"active\":1},{\"url\":\"https://testesbd-beta.mkb.kz:8078/IICWebservice.asmx\",\"active\":0}]",
  "passed": "------------------------PASSED------------------------",
  "failed": "------------------------FAILED------------------------"
}